opentherm_web_api/__init__.py
opentherm_web_api/const.py
opentherm_web_api/opentherm_controller.py
opentherm_web_api/opentherm_web_api.py
opentherm_web_api-0.1.6.dist-info/LICENSE
opentherm_web_api-0.1.6.dist-info/METADATA
opentherm_web_api-0.1.6.dist-info/WHEEL
opentherm_web_api-0.1.6.dist-info/top_level.txt
opentherm_web_api-0.1.6.dist-info/RECORD
